MANIFEST.in
README.md
setup.py
bin/my_names2.bat
dkrywczuk.egg-info/PKG-INFO
dkrywczuk.egg-info/SOURCES.txt
dkrywczuk.egg-info/dependency_links.txt
dkrywczuk.egg-info/requires.txt
dkrywczuk.egg-info/top_level.txt
my_names2_pac/__init__.py
my_names2_pac/my_names2.py