Metadata-Version: 2.1
Name: dkrywczuk
Version: 1.0.0
Summary: Generate random names with lenght
Home-page:  
Author: Damian Krywczuk
Author-email: methanoli@gmail.com
License: UNKNOWN
Keywords: random names
Platform: UNKNOWN
